src/__init__.py
src/_chart_types.py
src/indicadores.py
dash_tools_reflejar-0.1.1.dist-info/METADATA
dash_tools_reflejar-0.1.1.dist-info/WHEEL
dash_tools_reflejar-0.1.1.dist-info/RECORD
